openpyxl_autofill/__init__.py
openpyxl_autofill/_formula.py
openpyxl_autofill/_insert.py
openpyxl_autofill/_range.py
openpyxl_autofill/_utils.py
openpyxl_autofill/delete.py
openpyxl_autofill/insert.py
openpyxl_autofill/sort.py
openpyxl_autofill/tests/__init__.py
openpyxl_autofill/tests/delete_test.py
openpyxl_autofill/tests/formula_test.py
openpyxl_autofill/tests/insert_test.py
openpyxl_autofill/tests/sort_test.py
openpyxl_autofill-0.2.2.dist-info/LICENSE
openpyxl_autofill-0.2.2.dist-info/METADATA
openpyxl_autofill-0.2.2.dist-info/WHEEL
openpyxl_autofill-0.2.2.dist-info/top_level.txt
openpyxl_autofill-0.2.2.dist-info/RECORD
