Metadata-Version: 2.1
Name: openpyxl_autofill
Version: 0.2.2
Summary: 针对openpyxl的功能扩展
Home-page: https://github.com/taohoo/openpyxl_autofill
Author: HuBo
Author-email: taohoo@163.com
License: MIT License
Platform: all
Classifier: Programming Language :: Python :: 3
Classifier: Programming Language :: Python :: Implementation :: CPython
Classifier: Programming Language :: Python :: Implementation :: PyPy
Requires-Python: >=3.8
License-File: LICENSE
Requires-Dist: openpyxl
